odoo10_addon_crm_claim_rma-10.0.1.0.0.99.dev5-py2.7-nspkg.pth
odoo/addons/crm_claim_rma/README.rst
odoo/addons/crm_claim_rma/__init__.py
odoo/addons/crm_claim_rma/__manifest__.py
odoo/addons/crm_claim_rma/data/crm_claim_category.xml
odoo/addons/crm_claim_rma/data/crm_team.xml
odoo/addons/crm_claim_rma/data/ir_sequence_type.xml
odoo/addons/crm_claim_rma/i18n/de.po
odoo/addons/crm_claim_rma/i18n/es.po
odoo/addons/crm_claim_rma/i18n/es_MX.po
odoo/addons/crm_claim_rma/i18n/es_PA.po
odoo/addons/crm_claim_rma/i18n/es_VE.po
odoo/addons/crm_claim_rma/i18n/fr.po
odoo/addons/crm_claim_rma/i18n/pt_BR.po
odoo/addons/crm_claim_rma/i18n/ro.po
odoo/addons/crm_claim_rma/i18n/sl.po
odoo/addons/crm_claim_rma/models/__init__.py
odoo/addons/crm_claim_rma/models/account_invoice.py
odoo/addons/crm_claim_rma/models/account_invoice_line.py
odoo/addons/crm_claim_rma/models/claim_line.py
odoo/addons/crm_claim_rma/models/crm_claim.py
odoo/addons/crm_claim_rma/models/invoice_no_date.py
odoo/addons/crm_claim_rma/models/procurement_group.py
odoo/addons/crm_claim_rma/models/product_no_supplier.py
odoo/addons/crm_claim_rma/models/stock_move.py
odoo/addons/crm_claim_rma/models/stock_picking.py
odoo/addons/crm_claim_rma/models/substate_substate.py
odoo/addons/crm_claim_rma/security/ir.model.access.csv
odoo/addons/crm_claim_rma/static/description/icon.png
odoo/addons/crm_claim_rma/tests/__init__.py
odoo/addons/crm_claim_rma/tests/test_claim.py
odoo/addons/crm_claim_rma/tests/test_picking_creation.py
odoo/addons/crm_claim_rma/views/account_invoice.xml
odoo/addons/crm_claim_rma/views/claim_line.xml
odoo/addons/crm_claim_rma/views/crm_claim.xml
odoo/addons/crm_claim_rma/views/res_partner.xml
odoo/addons/crm_claim_rma/views/stock_view.xml
odoo/addons/crm_claim_rma/wizards/__init__.py
odoo/addons/crm_claim_rma/wizards/account_invoice_refund.py
odoo/addons/crm_claim_rma/wizards/claim_make_picking.py
odoo/addons/crm_claim_rma/wizards/claim_make_picking.xml
odoo10_addon_crm_claim_rma-10.0.1.0.0.99.dev5.dist-info/METADATA
odoo10_addon_crm_claim_rma-10.0.1.0.0.99.dev5.dist-info/RECORD
odoo10_addon_crm_claim_rma-10.0.1.0.0.99.dev5.dist-info/WHEEL
odoo10_addon_crm_claim_rma-10.0.1.0.0.99.dev5.dist-info/namespace_packages.txt
odoo10_addon_crm_claim_rma-10.0.1.0.0.99.dev5.dist-info/top_level.txt
