Metadata-Version: 2.1
Name: odoo10-addon-crm-claim-rma
Version: 10.0.1.0.0.99.dev5
Summary: RMA Claim (Product Return Management)
Home-page: https://github.com/OCA/rma
Author: Akretion, Camptocamp, Eezee-it, MONK Software, Vauxoo, Techspawn Solutions, Odoo Community Association (OCA)
Author-email: support@odoo-community.org
License: AGPL-3
Platform: UNKNOWN
Classifier: Programming Language :: Python
Classifier: Framework :: Odoo
Classifier: License :: OSI Approved :: GNU Affero General Public License v3
Requires-Python: ~=2.7
Requires-Dist: odoo10-addon-crm-claim-rma-code
Requires-Dist: odoo10-addon-crm-rma-location
Requires-Dist: odoo10-addon-product-warranty
Requires-Dist: odoo (<10.1dev,>=10.0)
